w01fm00n/__init__.py
w01fm00n/main.py
w01fm00n/program.py
w01fm00n-0.3.3.dist-info/LICENSE
w01fm00n-0.3.3.dist-info/METADATA
w01fm00n-0.3.3.dist-info/WHEEL
w01fm00n-0.3.3.dist-info/entry_points.txt
w01fm00n-0.3.3.dist-info/top_level.txt
w01fm00n-0.3.3.dist-info/RECORD
