Metadata-Version: 2.1
Name: w01fm00n
Version: 0.3.3
Summary: terminal-based forensic utility
Home-page: https://github.com/w01fdev/w01fm00n
Author: w01f
Author-email: w01f@w01f.dev
License: GPL-3.0
Platform: UNKNOWN
Classifier: Development Status :: 5 - Production/Stable
Classifier: Programming Language :: Python :: 3.3
Classifier: Programming Language :: Python :: 3.4
Classifier: Programming Language :: Python :: 3.5
Classifier: Programming Language :: Python :: 3.6
Classifier: Programming Language :: Python :: 3.7
Classifier: Programming Language :: Python :: 3.8
Requires-Python: >=3.3
